ideaseed/__init__.py
ideaseed/authentication.py
ideaseed/cli.py
ideaseed/config_wizard.py
ideaseed/constants.py
ideaseed/github_cards.py
ideaseed/gkeep.py
ideaseed/interactive_mode.py
ideaseed/ondisk.py
ideaseed/ui.py
ideaseed/update_checker.py
ideaseed/utils.py
ideaseed-1.2.2.dist-info/entry_points.txt
ideaseed-1.2.2.dist-info/LICENSE
ideaseed-1.2.2.dist-info/WHEEL
ideaseed-1.2.2.dist-info/METADATA
ideaseed-1.2.2.dist-info/RECORD
