Metadata-Version: 2.1
Name: ideaseed
Version: 1.2.2
Summary: Note down your ideas and get them to the right place, without switching away from your terminal
Home-page: https://github.com/ewen-lbh/ideaseed
License: MIT
Author: Ewen Le Bihan
Author-email: ewen.lebihan7@gmail.com
Requires-Python: >=3.6,<4.0
Classifier: License :: OSI Approved :: MIT License
Classifier: Programming Language :: Python :: 3
Classifier: Programming Language :: Python :: 3.6
Classifier: Programming Language :: Python :: 3.7
Classifier: Programming Language :: Python :: 3.8
Classifier: Programming Language :: Python :: 3.9
Requires-Dist: PyGithub (>=1.54.1,<2.0.0)
Requires-Dist: PyYAML (>=5.4.1,<6.0.0)
Requires-Dist: docopt (>=0.6.2,<0.7.0)
Requires-Dist: gkeepapi (>=0.11.16,<0.12.0)
Requires-Dist: inquirer (>=2.7.0,<3.0.0)
Requires-Dist: recordclass (>=0.14.3,<0.15.0)
Requires-Dist: rich (>=10.1.0,<11.0.0)
Requires-Dist: semantic-version (>=2.8.5,<3.0.0)
Requires-Dist: unicode-slugify (>=0.1.3,<0.2.0)
Requires-Dist: urllib3 (>=1.26.4,<2.0.0)
Project-URL: Repository, https://github.com/ewen-lbh/ideaseed
